canlab/__init__.py
canlab-0.1.6.dist-info/licenses/LICENSE
conversions/__init__.py
dbc/__init__.py
dbc/dbc_data.py
dbc/dbc_loader.py
dbc/message_data.py
dbc/util.py
decoder/__init__.py
decoder/frame_decoder.py
encoder/__init__.py
encoder/frame_encoder.py
exceptions/__init__.py
exceptions/dbc_exception.py
exceptions/id_exception.py
exceptions/signal_format_exception.py
log_reader/__init__.py
log_reader/asc.py
canlab-0.1.6.dist-info/METADATA
canlab-0.1.6.dist-info/WHEEL
canlab-0.1.6.dist-info/top_level.txt
canlab-0.1.6.dist-info/RECORD
