Metadata-Version: 2.4
Name: canlab
Version: 0.1.6
Summary: A general CAN framework API for Python - encode/decode CAN frames, parse DBC files, and work with CAN log files
Author: Peter Kwaterski
License: MIT
Keywords: can,dbc,automotive,can-bus,frame,encoder,decoder
Classifier: Development Status :: 4 - Beta
Classifier: Intended Audience :: Developers
Classifier: License :: OSI Approved :: MIT License
Classifier: Programming Language :: Python :: 3
Classifier: Programming Language :: Python :: 3.12
Classifier: Topic :: Software Development :: Libraries :: Python Modules
Classifier: Topic :: Scientific/Engineering
Requires-Python: >=3.12
License-File: LICENSE
Requires-Dist: polars>=1.36.1
Provides-Extra: dev
Requires-Dist: pytest>=7.4.0; extra == "dev"
Requires-Dist: pytest-cov>=4.1.0; extra == "dev"
Dynamic: license-file
